build/__init__.py
build/lib/__init__.py
build/lib/geocitysorter/__init__.py
build/lib/geocitysorter/census.py
build/lib/geocitysorter/citycoords.py
build/lib/geocitysorter/example.py
build/lib/geocitysorter/populations.py
build/lib/geocitysorter/utils.py
geocitysorter/__init__.py
geocitysorter/census.py
geocitysorter/geocitysorter.py
geocitysorter/populations.py
geocitysorter/geodata/capitals.csv
geocitysorter/geodata/geocitysorter.py
geocitysorter/geodata/incorporated_cities_uscensus.json
geocitysorter/geodata/incorporated_cities_uscensus_lower48.json
geocitysorter/geodata/incorporated_cities_uscensus_min.json
geocitysorter-0.9.12.dist-info/LICENSE
geocitysorter-0.9.12.dist-info/METADATA
geocitysorter-0.9.12.dist-info/WHEEL
geocitysorter-0.9.12.dist-info/top_level.txt
geocitysorter-0.9.12.dist-info/RECORD
