Metadata-Version: 2.1
Name: geocitysorter
Version: 0.9.12
Summary: geographic relevance sorter for geopandas dataframes
Author-email: Tony Rice <rtphokie+pypi@gmail.com>
Project-URL: Homepage, https://github.com/rtphokie/geocitysorter
Project-URL: Issues, https://github.com/rtphokie/geocitysorter/issues
Classifier: Programming Language :: Python :: 3
Classifier: License :: OSI Approved :: MIT License
Classifier: Operating System :: OS Independent
Requires-Python: >=3.9
License-File: LICENSE
Requires-Dist: geopandas >=0.14.1
Requires-Dist: requests >=2.31.0
Requires-Dist: requests-cache >=1.1.1
Requires-Dist: geopy >=2.4.1
